[
  {
    "control": {
      "Package": "git.shin.complications",
      "Name": "Complications",
      "Version": "3.0",
      "Section": "Tweaks",
      "Architecture": "iphoneos-arm",
      "Depends": "mobilesubstrate",
      "Author": "Ben Giannis",
      "Description": "watchOS widgets on your lock screen",
      "Homepage": "https://tachibana-shin.github.io/repo",
      "Maintainer": "tachibana-shin<tachib.shin@gmail.com>",
      "Sponsor": "tachibana-shin<https://tachibana-shin.github.io>",
      "Depiction": "https://tachibana-shin.github.io/repo/package/git.shin.complications"
    },
    "MD5sum": "81016f38739aa319ddcf4f84a83e00c3",
    "SHA256sum": "115fcea76dcd54d5c11b4508f4a8312c57abfa41f462792e597a2a4ab18ceef2",
    "SHA512sum": "2a0041fc4456e5190204b5df5f3b744bafc91dc790a7aa7396bfa8871426bca46fa6899eb8be8bb05caf42de20c5ba4dfd2db6da3d44edbda04a00ece5301436",
    "size": 475384,
    "birthtimeMs": 1638251121219.0251,
    "uid": 11297
  }
]